{
  "imdbId": "archive-karakolda-ayna-var_movie",
  "title": "Karakolda Ayna Var, Turkish Movie",
  "sources": [
    {
      "type": "archive.org",
      "url": "https://archive.org/details/karakolda-ayna-var_movie",
      "title": "Karakolda Ayna Var, Turkish Movie",
      "description": "Karakolda Ayna Var, Turkish Movie",
      "fileSize": 900414011,
      "id": "karakolda-ayna-var_movie"
    }
  ],
  "relatedMovies": [],
  "collections": [],
  "is_curated": false,
  "verified": false,
  "lastUpdated": "2026-01-07T00:09:15.998Z"
}