{
  "imdbId": "archive-the-2-mrs.-carrolls",
  "title": "The 2 Mrs. Carrolls (Humphrey Bogart)",
  "year": 1947,
  "sources": [
    {
      "type": "archive.org",
      "url": "https://archive.org/details/the-2-mrs.-carrolls",
      "title": "The 2 Mrs. Carrolls (Humphrey Bogart)",
      "description": "Another classic Bogart noir mystery, suspense,  thriller in which he knocks off wifes like he did in \"Conflict.\"",
      "id": "the-2-mrs.-carrolls"
    }
  ],
  "relatedMovies": [],
  "collections": [],
  "is_curated": false,
  "verified": false,
  "qualityLabels": [],
  "lastUpdated": "2025-12-25T23:14:07.574Z"
}