{
  "imdbId": "archive-1944-double-exposure-william-berke-vo",
  "title": "1944 - Double Exposure - William Berke - VO",
  "year": 1944,
  "sources": [
    {
      "type": "archive.org",
      "url": "https://archive.org/details/1944-double-exposure-william-berke-vo",
      "id": "1944-double-exposure-william-berke-vo",
      "title": "1944 - Double Exposure - William Berke - VO",
      "description": "For Academic / Educational Use Only derechonoir.wordpress.com",
      "fileSize": 166369392,
      "addedAt": "2026-01-07T00:06:03.997Z",
      "thumbnail": "https://archive.org/services/img/1944-double-exposure-william-berke-vo",
      "year": 1944,
      "collection": "feature_films",
      "downloads": 1718
    }
  ],
  "relatedMovies": [],
  "collections": [],
  "is_curated": false,
  "verified": false,
  "lastUpdated": "2026-01-07T00:06:03.997Z"
}