{
  "movieId": "archive-805926668927",
  "title": "Nacido para matar 1947 born to kill",
  "sources": [
    {
      "type": "archive.org",
      "url": "https://archive.org/details/805926668927",
      "id": "805926668927",
      "title": "Nacido para matar 1947 born to kill",
      "description": "Cine Negro ",
      "fileSize": 786482259,
      "addedAt": "2026-01-07T00:06:09.632Z",
      "thumbnail": "https://archive.org/services/img/805926668927",
      "collection": "feature_films",
      "downloads": 25
    }
  ],
  "relatedMovies": [],
  "collections": [],
  "is_curated": false,
  "verified": false,
  "lastUpdated": "2026-01-07T00:06:09.632Z"
}