{
  "imdbId": "tt0023934",
  "title": "Deadwood Pass",
  "year": 1933,
  "sources": [
    {
      "type": "youtube",
      "url": "https://www.youtube.com/watch?v=MM__rDrJcQc",
      "title": "Deadwood Pass (1933) TOM TYLER",
      "description": "Stars: Tom Tyler, Hal Taliaferro, Lafe McKee\n Director: J.P. McGowan\n\n The Hawk has broken out of prison and the Sheriff and Sorrenson have a plan to have Whitlock pose as the Hawk, infiltrate the gang, and recover the stolen bonds. All goes well until The Chief who knows the real Hawk arrives.",
      "id": "MM__rDrJcQc",
      "channelName": "PizzaFlix",
      "channelId": "UCE34fwgW7kWr7tc7YiOWtRw"
    }
  ],
  "metadata": {
    "Rated": "Passed",
    "Runtime": "62 min",
    "imdbRating": 5.6,
    "imdbVotes": 81,
    "Genre": "Western",
    "Plot": "The Hawk has broken out of prison and the Sheriff and Sorrenson have a plan to have Whitlock pose as the Hawk, infiltrate the gang, and recover the stolen bonds. All goes well until The Chief who knows the real Hawk arrives.",
    "Director": "J.P. McGowan",
    "Writer": "Oliver Drake, J. Wesley Patterson",
    "Actors": "Tom Tyler, Hal Taliaferro, Lafe McKee",
    "Language": "English",
    "Country": "United States",
    "Awards": "N/A"
  },
  "relatedMovies": [
    {
      "imdbId": "tt0024766",
      "title": "When a Man Rides Alone",
      "year": 1933,
      "imdbRating": 5.6,
      "imdbVotes": 83,
      "language": "English",
      "sourceType": "youtube",
      "channelName": "PizzaFlix"
    },
    {
      "imdbId": "tt0023967",
      "title": "Drum Taps",
      "year": 1933,
      "imdbRating": 5.5,
      "imdbVotes": 83,
      "language": "English",
      "sourceType": "youtube",
      "channelName": "PizzaFlix"
    },
    {
      "imdbId": "tt0021176",
      "title": "Near the Rainbow's End",
      "year": 1930,
      "imdbRating": 6.1,
      "imdbVotes": 63,
      "language": "English",
      "sourceType": "youtube",
      "channelName": "PizzaFlix"
    },
    {
      "imdbId": "tt0023428",
      "title": "The Scarlet Brand",
      "year": 1932,
      "imdbVotes": 12,
      "language": "English",
      "sourceType": "youtube",
      "channelName": "PizzaFlix"
    },
    {
      "imdbId": "tt0023191",
      "title": "Mark of the Spur",
      "year": 1932,
      "imdbRating": 5.7,
      "imdbVotes": 58,
      "language": "English",
      "sourceType": "youtube",
      "channelName": "PizzaFlix"
    },
    {
      "imdbId": "tt0022291",
      "title": "Quick Trigger Lee",
      "year": 1931,
      "imdbRating": 4.1,
      "imdbVotes": 27,
      "language": "English",
      "sourceType": "youtube",
      "channelName": "PizzaFlix"
    },
    {
      "imdbId": "tt0021502",
      "title": "Under Texas Skies",
      "year": 1930,
      "imdbRating": 5.7,
      "imdbVotes": 79,
      "language": "English",
      "sourceType": "archive.org"
    },
    {
      "imdbId": "tt0030686",
      "title": "Roaring Six Guns",
      "year": 1937,
      "imdbRating": 6.3,
      "imdbVotes": 69,
      "language": "English",
      "sourceType": "youtube",
      "channelName": "PizzaFlix"
    },
    {
      "imdbId": "tt0026999",
      "title": "The Silver Bullet",
      "year": 1935,
      "imdbRating": 4.4,
      "imdbVotes": 37,
      "language": "English",
      "sourceType": "youtube",
      "channelName": "Cult Cinema Classics"
    },
    {
      "imdbId": "tt0018654",
      "title": "Arizona Days",
      "year": 1928,
      "imdbRating": 5.7,
      "imdbVotes": 56,
      "language": "English",
      "sourceType": "archive.org"
    },
    {
      "imdbId": "tt0030970",
      "title": "Where the West Begins",
      "year": 1938,
      "imdbRating": 5,
      "imdbVotes": 58,
      "language": "English",
      "sourceType": "archive.org"
    },
    {
      "imdbId": "tt0132279",
      "title": "Lightning Range",
      "year": 1933,
      "imdbRating": 3.8,
      "imdbVotes": 29,
      "language": "English",
      "sourceType": "youtube",
      "channelName": "PizzaFlix"
    }
  ],
  "collections": [],
  "is_curated": true,
  "verified": false,
  "lastUpdated": "2025-12-28T22:39:28.356Z"
}