{
  "imdbId": "tt0041109",
  "title": "Alimony",
  "year": 1949,
  "sources": [
    {
      "type": "archive.org",
      "url": "https://archive.org/details/Alimony",
      "title": "Alimony",
      "description": "Small town girl Kitty Traves (Martha Vickers) comes to New York with the idea of getting rich fast. Beginning as a 'model' she then becomes a divorce co-respondent in hotel room frame-ups. When her songwriting boyfriend, Dan Barker (John Beal), runs out of songs and money, she send him back to his loyal, true-blue fiancée, Linda Waring (Hillary Brooke). She moves on to marry a wealth industrialist, with divorce and alimony her only goal.",
      "id": "Alimony"
    },
    {
      "type": "youtube",
      "url": "https://www.youtube.com/watch?v=g5_uSBcuGi4",
      "title": "Alimony (1949) CRIME-DRAMA",
      "description": "Stars: Martha Vickers, John Beal, Hillary Brooke\n Director: Alfred Zeisler\n\n A promising young composer is tempted away from his devoted wife by a fortune-seeking woman who cares more for his prospects than for him.",
      "id": "g5_uSBcuGi4",
      "channelName": "PizzaFlix",
      "channelId": "UCE34fwgW7kWr7tc7YiOWtRw"
    }
  ],
  "metadata": {
    "Rated": "Approved",
    "Runtime": "70 min",
    "imdbRating": "5.3",
    "imdbVotes": "175",
    "Genre": "Crime, Drama, Music",
    "Plot": "Small town girl Kitty Traves comes to New York with the idea of getting rich fast. Beginning as a 'model' she then becomes a divorce co-respondent in hotel room frame-ups. When her songwriting boyfriend, Dan Barker, runs out of songs and money, she send him back to his loyal, true-blue fiancée, Linda Waring. She moves on to marry a wealth industrialist, with divorce and alimony her only goal.",
    "Director": "Alfred Zeisler",
    "Writer": "George Bricker, Royal K. Cole, Lawrence Lipton",
    "Actors": "Martha Vickers, John Beal, Hillary Brooke",
    "Language": "English",
    "Country": "United States",
    "Awards": "N/A"
  },
  "relatedMovies": [
    {
      "imdbId": "tt0041733",
      "title": "Parole, Inc.",
      "year": 1948,
      "imdbRating": "5.7",
      "imdbVotes": "421",
      "language": "English",
      "sourceType": "youtube",
      "channelName": "Timeless Classic Movies"
    },
    {
      "imdbId": "tt0039187",
      "title": "Big Town After Dark",
      "year": 1947,
      "imdbRating": "5.5",
      "imdbVotes": "299",
      "language": "English",
      "sourceType": "archive.org"
    },
    {
      "imdbId": "tt0041503",
      "title": "Impact",
      "year": 1949,
      "imdbRating": "7.0",
      "imdbVotes": "5,035",
      "language": "English, Cantonese",
      "sourceType": "archive.org"
    },
    {
      "imdbId": "tt0054817",
      "title": "Five Minutes to Live",
      "year": 1961,
      "imdbRating": "5.5",
      "imdbVotes": "1,009",
      "language": "English",
      "sourceType": "archive.org"
    },
    {
      "imdbId": "tt0041268",
      "title": "Criss Cross",
      "year": 1949,
      "imdbRating": "7.4",
      "imdbVotes": "10,070",
      "language": "English",
      "sourceType": "archive.org"
    },
    {
      "imdbId": "tt0041555",
      "title": "Knock on Any Door",
      "year": 1949,
      "imdbRating": "6.6",
      "imdbVotes": "4,414",
      "language": "English, Italian, Latin",
      "sourceType": "archive.org"
    },
    {
      "imdbId": "tt0041761",
      "title": "Port of New York",
      "year": 1949,
      "imdbRating": "6.0",
      "imdbVotes": "1,105",
      "language": "English",
      "sourceType": "archive.org"
    },
    {
      "imdbId": "tt0041269",
      "title": "The Crooked Way",
      "year": 1949,
      "imdbRating": "6.6",
      "imdbVotes": "1,671",
      "language": "English",
      "sourceType": "archive.org"
    },
    {
      "imdbId": "tt0041786",
      "title": "The Reckless Moment",
      "year": 1949,
      "imdbRating": "7.1",
      "imdbVotes": "6,042",
      "language": "English",
      "sourceType": "archive.org"
    },
    {
      "imdbId": "tt0042006",
      "title": "The Undercover Man",
      "year": 1949,
      "imdbRating": "6.6",
      "imdbVotes": "1,454",
      "language": "English, Italian",
      "sourceType": "archive.org"
    },
    {
      "imdbId": "tt0041958",
      "title": "Thieves' Highway",
      "year": 1949,
      "imdbRating": "7.5",
      "imdbVotes": "7,130",
      "language": "English, Italian, Greek",
      "sourceType": "archive.org"
    },
    {
      "imdbId": "tt0041967",
      "title": "Tokyo Joe",
      "year": 1949,
      "imdbRating": "6.3",
      "imdbVotes": "2,918",
      "language": "English, Japanese",
      "sourceType": "archive.org"
    }
  ],
  "collections": [],
  "is_curated": true,
  "verified": false,
  "qualityLabels": [],
  "lastUpdated": "2025-12-29T01:59:54.204Z"
}