{
  "imdbId": "tt0030686",
  "title": "Roaring Six Guns",
  "year": 1937,
  "sources": [
    {
      "type": "youtube",
      "url": "https://www.youtube.com/watch?v=2PrPRaP2PoY",
      "title": "Roaring Six Guns (1937) KERMIT MAYNARD",
      "description": "Stars: Kermit Maynard, Mary Hayes, Sam Flint\n Director: J.P. McGowan\n\n Sinclair has a government lease on range land that is about to expire. George Ringold wants the land and hires Roberts and his men. But they turn out to be a gang of killers and trouble soon arises.",
      "id": "2PrPRaP2PoY",
      "channelName": "PizzaFlix",
      "channelId": "UCE34fwgW7kWr7tc7YiOWtRw"
    }
  ],
  "metadata": {
    "Rated": "Passed",
    "Runtime": "57 min",
    "imdbRating": 6.3,
    "imdbVotes": 69,
    "Genre": "Western",
    "Plot": "Sinclair has a government lease on range land that is about to expire. George Ringold wants the land and hires Roberts and his men. But they turn out to be a gang of killers and trouble soon arises.",
    "Director": "J.P. McGowan",
    "Writer": "Arthur Everett, James Oliver Curwood",
    "Actors": "Kermit Maynard, Mary Hayes, Sam Flint",
    "Language": "English",
    "Country": "United States",
    "Awards": "N/A"
  },
  "relatedMovies": [
    {
      "imdbId": "tt0030970",
      "title": "Where the West Begins",
      "year": 1938,
      "imdbRating": 5,
      "imdbVotes": 58,
      "language": "English",
      "sourceType": "archive.org"
    },
    {
      "imdbId": "tt0023967",
      "title": "Drum Taps",
      "year": 1933,
      "imdbRating": 5.5,
      "imdbVotes": 83,
      "language": "English",
      "sourceType": "youtube",
      "channelName": "PizzaFlix"
    },
    {
      "imdbId": "tt0024766",
      "title": "When a Man Rides Alone",
      "year": 1933,
      "imdbRating": 5.6,
      "imdbVotes": 83,
      "language": "English",
      "sourceType": "youtube",
      "channelName": "PizzaFlix"
    },
    {
      "imdbId": "tt0023934",
      "title": "Deadwood Pass",
      "year": 1933,
      "imdbRating": 5.6,
      "imdbVotes": 81,
      "language": "English",
      "sourceType": "youtube",
      "channelName": "PizzaFlix"
    },
    {
      "imdbId": "tt0018654",
      "title": "Arizona Days",
      "year": 1928,
      "imdbRating": 5.7,
      "imdbVotes": 56,
      "language": "English",
      "sourceType": "archive.org"
    },
    {
      "imdbId": "tt0021502",
      "title": "Under Texas Skies",
      "year": 1930,
      "imdbRating": 5.7,
      "imdbVotes": 79,
      "language": "English",
      "sourceType": "archive.org"
    },
    {
      "imdbId": "tt0022291",
      "title": "Quick Trigger Lee",
      "year": 1931,
      "imdbRating": 4.1,
      "imdbVotes": 27,
      "language": "English",
      "sourceType": "youtube",
      "channelName": "PizzaFlix"
    },
    {
      "imdbId": "tt0023428",
      "title": "The Scarlet Brand",
      "year": 1932,
      "imdbVotes": 12,
      "language": "English",
      "sourceType": "youtube",
      "channelName": "PizzaFlix"
    },
    {
      "imdbId": "tt0132951",
      "title": "The Fighting Texan",
      "year": 1937,
      "imdbRating": 6.9,
      "imdbVotes": 16,
      "language": "English",
      "sourceType": "youtube",
      "channelName": "PizzaFlix"
    },
    {
      "imdbId": "tt0021176",
      "title": "Near the Rainbow's End",
      "year": 1930,
      "imdbRating": 6.1,
      "imdbVotes": 63,
      "language": "English",
      "sourceType": "youtube",
      "channelName": "PizzaFlix"
    },
    {
      "imdbId": "tt0132990",
      "title": "Galloping Dynamite",
      "year": 1937,
      "imdbRating": 6.1,
      "imdbVotes": 26,
      "language": "English",
      "sourceType": "youtube",
      "channelName": "PizzaFlix"
    },
    {
      "imdbId": "tt0023191",
      "title": "Mark of the Spur",
      "year": 1932,
      "imdbRating": 5.7,
      "imdbVotes": 58,
      "language": "English",
      "sourceType": "youtube",
      "channelName": "PizzaFlix"
    }
  ],
  "collections": [],
  "is_curated": true,
  "verified": false,
  "lastUpdated": "2025-12-28T22:40:02.423Z"
}