{
  "imdbId": "tt0151354",
  "title": "Little Boy with a Big Horn",
  "year": 1953,
  "sources": [
    {
      "type": "archive.org",
      "url": "https://archive.org/details/little-boy-with-a-big-horn-1953",
      "id": "little-boy-with-a-big-horn-1953",
      "title": "Little Boy with a Big Horn (1953)",
      "description": "Ollie loves to play the tuba but his playing upsets all the people in town. He goes to the country and disrupts the milking habits of the cows. He finally takes a boat and practices at sea in order not to disturb anyone. His tuba-playing saves a ship from going on the rocks and he becomes a town hero. Watch on RetroFlix:  https://retroflix.org/little-boy-with-a-big-horn-1953/",
      "fileSize": 51700251,
      "addedAt": "2026-01-07T00:09:38.891Z",
      "thumbnail": "https://archive.org/services/img/little-boy-with-a-big-horn-1953",
      "language": "eng",
      "year": 1953,
      "collection": "feature_films",
      "downloads": 55
    }
  ],
  "metadata": {
    "Rated": "N/A",
    "Runtime": "7 min",
    "imdbRating": 6.7,
    "imdbVotes": 36,
    "Genre": "Animation, Short",
    "Plot": "Ollie loves to play the tuba but his playing upsets all the people in town. He goes to the country and disrupts the milking habits of the cows. He finally takes a boat and practices at sea in order not to disturb anyone. His tuba-playing saves a ship from going on the rocks and he becomes a town hero.",
    "Director": "Robert Cannon",
    "Writer": "Jack Bechdolt, T. Hee, Robert Cannon",
    "Actors": "John T. Smith, Marian Richman",
    "Language": "English",
    "Country": "United States",
    "Awards": "N/A"
  },
  "relatedMovies": [
    "tt0045626",
    "tt0149779",
    "tt0148317",
    "tt0153850",
    "tt0150123",
    "tt0148209",
    "tt0049258",
    "tt0150663",
    "tt0151840",
    "tt0049380",
    "tt0151460",
    "tt0152314"
  ],
  "collections": [],
  "is_curated": true,
  "verified": false,
  "lastUpdated": "2026-01-07T00:09:38.891Z"
}