{
  "movieId": "tt0105315",
  "title": "Sapne Saajan Ke",
  "year": 1992,
  "sources": [
    {
      "type": "archive.org",
      "url": "https://archive.org/details/sapne-saajan-ke-1992-dv-drip-x-264-aac-5.1-chapters-esub",
      "id": "sapne-saajan-ke-1992-dv-drip-x-264-aac-5.1-chapters-esub",
      "title": "Sapne Saajan Ke 1992 Dv DRip X 264 AAC 5.1 Chapters Esub",
      "description": "Sapne Saajan Ke",
      "fileSize": 2551789586,
      "addedAt": "2026-01-07T00:10:40.952Z",
      "thumbnail": "https://archive.org/services/img/sapne-saajan-ke-1992-dv-drip-x-264-aac-5.1-chapters-esub",
      "collection": "feature_films",
      "downloads": 27
    }
  ],
  "metadata": {
    "Rated": "Not Rated",
    "Runtime": "162 min",
    "imdbRating": 3.3,
    "imdbVotes": 179,
    "Genre": "Drama, Romance",
    "Plot": "Shalini wants her daughter, Jyoti, to get married with son of a wealthy man, Gulu. But Jyoti doesn't like Gulu. She meets Deepak and both fall in love. Shalini approves this match of Jyoti and Deepak. But Jyoti comes to know that Deepak is not a rich boy as he pretended all along the way.",
    "Director": "Lawrence D'Souza",
    "Writer": "Mushtaq Merchant",
    "Actors": "Jackie Shroff, Dimple Kapadia, Karisma Kapoor",
    "Language": "Hindi",
    "Country": "India",
    "Awards": "1 nomination"
  },
  "relatedMovies": [
    "tt0267905",
    "tt0102825",
    "tt0105313",
    "tt0376182",
    "tt0108109",
    "tt0104561",
    "tt0102200",
    "tt0105271",
    "tt8856296",
    "tt0104350",
    "tt0107273",
    "tt0103205"
  ],
  "collections": [],
  "is_curated": true,
  "verified": false,
  "lastUpdated": "2026-02-02T00:36:59.130Z"
}