{
  "imdbId": "tt0149273",
  "title": "Tooth or Consequences",
  "year": 1947,
  "sources": [
    {
      "type": "archive.org",
      "url": "https://archive.org/details/tooth-or-consequences-1947",
      "id": "tooth-or-consequences-1947",
      "title": "Tooth or Consequences (1947)",
      "description": "The Fox, once again, is plagued with a toothache, and once again is in search for a dentist to relieve his agony, and he, once again, finds Mr. Crow, pretending to be a dentist. This leads to no end of painful consequences for Mr. Fox. Watch on RetroFlix:  https://retroflix.org/tooth-or-consequences-1947/",
      "fileSize": 194701445,
      "addedAt": "2026-01-07T00:12:44.285Z",
      "thumbnail": "https://archive.org/services/img/tooth-or-consequences-1947",
      "language": "eng",
      "year": 1947,
      "collection": "feature_films",
      "downloads": 131
    }
  ],
  "metadata": {
    "Rated": "Approved",
    "Runtime": "7 min",
    "imdbVotes": 14,
    "Genre": "Animation, Short, Comedy",
    "Plot": "The Fox, once again, is plagued with a toothache, and once again is in search for a dentist to relieve his agony, and he, once again, finds Mr. Crow, pretending to be a dentist. This leads to no end of painful consequences for Mr....",
    "Director": "Howard Swift",
    "Writer": "Cal Howard",
    "Actors": "Dave Barry, Cal Howard, Jack Mather",
    "Language": "English",
    "Country": "United States",
    "Awards": "N/A"
  },
  "relatedMovies": [
    "tt0148419",
    "tt0149316",
    "tt0149288",
    "tt0151321",
    "tt0162727",
    "tt0150052",
    "tt0148603",
    "tt0148014",
    "tt0148310",
    "tt0147918",
    "tt0148072",
    "tt0147949"
  ],
  "collections": [
    {
      "id": "animation-shorts",
      "name": "Animation Shorts"
    }
  ],
  "is_curated": true,
  "verified": false,
  "lastUpdated": "2026-01-07T00:12:44.285Z"
}