{
  "movieId": "tt2073643",
  "title": "Rüyalar Gerçek Olsa",
  "year": 1972,
  "sources": [
    {
      "type": "archive.org",
      "url": "https://archive.org/details/ruyalar-gercek-olsa_movie",
      "id": "ruyalar-gercek-olsa_movie",
      "title": "Rüyalar Gerçek Olsa, Turkish Movie",
      "description": "Rüyalar Gerçek Olsa, Turkish Movie",
      "fileSize": 689347451,
      "addedAt": "2026-01-07T00:10:40.951Z",
      "thumbnail": "https://archive.org/services/img/ruyalar-gercek-olsa_movie",
      "language": "tur",
      "collection": "feature_films",
      "downloads": 63
    }
  ],
  "metadata": {
    "Rated": "N/A",
    "Runtime": "68 min",
    "imdbRating": 5,
    "imdbVotes": 53,
    "Genre": "Comedy, Romance",
    "Plot": "N/A",
    "Director": "Hulki Saner",
    "Writer": "Oksal Pekmezoglu",
    "Actors": "Engin Çaglar, Esen Püsküllü, Müjdat Gezen",
    "Language": "Turkish",
    "Country": "Turkey",
    "Awards": "N/A"
  },
  "relatedMovies": [
    "tt0469681",
    "tt1694070",
    "tt6243202",
    "tt0182503",
    "tt0469636",
    "tt0067818",
    "tt0827739",
    "tt0253791",
    "tt0827748",
    "tt0462583",
    "tt0168469",
    "tt0068246"
  ],
  "collections": [],
  "is_curated": true,
  "verified": false,
  "lastUpdated": "2026-02-02T00:26:39.154Z"
}