{
  "imdbId": "tt7886442",
  "title": "Death Kiss",
  "year": 2018,
  "sources": [
    {
      "type": "youtube",
      "url": "https://www.youtube.com/watch?v=fXHpDNZ6op0",
      "title": "Death Kiss | Full Movie | Vigilante Action Crime Revenge | Robert Bronzi",
      "description": "A vigilante with a mysterious past becomes a one-man army in a crime-infested town as he takes the law into his own hands, at the same time protecting a young mother and her daughter.  He sets his sights on a local kingpin, setting up an action-packed and fateful confrontation.\n2018.  Stars: Robert Bronzi, Daniel Baldwin, Richard Tyson\n*Licensed from Uncork'd Entertainment. All rights reserved*\n\n*Welcome to Movie Central, SUBSCRIBE NOW!* - https://bit.ly/3mRDJox\n*MORE FREE MOVIES  on YouTube!* - \n🌟 Free Action Movies: https://bit.ly/3uMwRxq\n🌟 Free Sci-Fi Movies: https://bit.ly/3o3lLAm\n🌟 Free Horror Movies: https://bit.ly/3aBBt2J\n🌟 Free Asylum Movies: https://bit.ly/3cipzeI\n🌟 Free Crime/Thriller: https://bit.ly/3o01prJ\n🌟 Free Drama Movies: https://bit.ly/3Pu4mN9\n🌟 Free Comedy Movies: https://bit.ly/3IE0wPd\n🌟 Free Western Movies: https://bit.ly/3RqTX6u\n🌟 Free Adventure Movies: https://bit.ly/3yHolAT\n🌟 MOVIE CENTRAL Channel: https://bit.ly/3o27Fze\n\n** All of the content on this channel is under legal license from various copyright holders and distributors. We ask you to please contact us if you believe there are any copyright issues via - you_tube@valleyarm.com  **\n\n#Revenge #MovieCentral #FreeYouTubeMovies",
      "id": "fXHpDNZ6op0",
      "channelName": "Movie Central",
      "channelId": "UCGBzBkV-MinlBvHBzZawfLQ",
      "regionRestriction": {
        "allowed": [
          "CA",
          "US"
        ]
      }
    }
  ],
  "metadata": {
    "Rated": "N/A",
    "Runtime": "87 min",
    "imdbRating": "4.5",
    "imdbVotes": "1,605",
    "Genre": "Action, Crime, Drama",
    "Plot": "A vigilante with a mysterious past moves into a city that has been infested with crime and terror. He then takes the law into his own hands so that he can save and protect a young mother and her child.",
    "Director": "Rene Perez",
    "Writer": "Rene Perez",
    "Actors": "Robert Bronzi, Daniel Baldwin, Richard Tyson",
    "Language": "English",
    "Country": "United States",
    "Awards": "N/A"
  },
  "relatedMovies": [
    {
      "imdbId": "tt6170506",
      "title": "Beast of Burden",
      "year": 2018,
      "imdbRating": "3.6",
      "imdbVotes": "3,363",
      "language": "English, Spanish",
      "sourceType": "youtube",
      "channelName": "Movie Central"
    },
    {
      "imdbId": "tt3580692",
      "title": "Abducted",
      "year": 2018,
      "imdbRating": "4.0",
      "imdbVotes": "791",
      "language": "English",
      "sourceType": "youtube",
      "channelName": "Movie Central"
    },
    {
      "imdbId": "tt3881026",
      "title": "Rendel: Dark Vengeance",
      "year": 2017,
      "imdbRating": "4.6",
      "imdbVotes": "2,479",
      "language": "Finnish, English",
      "sourceType": "youtube",
      "channelName": "Popcornflix"
    },
    {
      "imdbId": "tt6830716",
      "title": "Expo",
      "year": 2019,
      "imdbRating": "2.6",
      "imdbVotes": "2,236",
      "language": "English",
      "sourceType": "youtube",
      "channelName": "Popcornflix"
    },
    {
      "imdbId": "tt4205896",
      "title": "Night Walk",
      "year": 2019,
      "imdbRating": "3.8",
      "imdbVotes": "3,046",
      "language": "English",
      "sourceType": "youtube",
      "channelName": "Netzkino"
    },
    {
      "imdbId": "tt5822564",
      "title": "The Kitchen",
      "year": 2019,
      "imdbRating": "5.6",
      "imdbVotes": "23,349",
      "language": "English, Hebrew",
      "sourceType": "youtube",
      "channelName": "Movie Central"
    },
    {
      "imdbId": "tt6067752",
      "title": "Lucifer",
      "year": 2019,
      "imdbRating": "7.5",
      "imdbVotes": "12,933",
      "language": "Malayalam",
      "sourceType": "youtube",
      "channelName": "Movie Central"
    },
    {
      "imdbId": "tt3263096",
      "title": "Boost",
      "year": 2017,
      "imdbRating": "4.0",
      "imdbVotes": "719",
      "language": "English",
      "sourceType": "youtube",
      "channelName": "Movie Central"
    },
    {
      "imdbId": "tt8385420",
      "title": "Operation Cicero",
      "year": 2019,
      "imdbRating": "6.5",
      "imdbVotes": "6,592",
      "language": "Turkish, German, English",
      "sourceType": "youtube",
      "channelName": "Movie Central"
    },
    {
      "imdbId": "tt7115466",
      "title": "Whiteblood",
      "year": 2017,
      "imdbRating": "6.2",
      "imdbVotes": "43",
      "language": "English, Spanish",
      "sourceType": "youtube",
      "channelName": "Movie Central"
    },
    {
      "imdbId": "tt3449322",
      "title": "Dirty Lies",
      "year": 2017,
      "imdbRating": "4.5",
      "imdbVotes": "471",
      "language": "English",
      "sourceType": "youtube",
      "channelName": "Movie Central"
    },
    {
      "imdbId": "tt10314450",
      "title": "Becky",
      "year": 2020,
      "imdbRating": "6.1",
      "imdbVotes": "28,095",
      "language": "English",
      "sourceType": "youtube",
      "channelName": "Movie Central"
    }
  ],
  "collections": [],
  "is_curated": true,
  "verified": false,
  "qualityLabels": [],
  "lastUpdated": "2025-12-29T02:08:32.559Z"
}