{
  "imdbId": "youtube-IVzuR4Gli-M",
  "title": "Relative Evil - Full Movie",
  "sources": [
    {
      "type": "youtube",
      "url": "https://www.youtube.com/watch?v=IVzuR4Gli-M",
      "title": "Relative Evil - Full Movie",
      "description": "When JJ (Jonathan Tucker) returns home from rehab, he is greeted by a conniving family who are plotting to cash in on a life insurance policy before his 18th birthday. Caught in a web of self-destruction, JJ struggles to stay clean in an environment overflowing with temptations and deceit. With a winning performance by Jonathan Tucker and a beguiling turn from Jennifer Tilly, this dark, pulp thriller shows Home Sweet Home really can be murder.\n\n2004\n\nDirector - Tanya Wexler\n\nCast - Jonathan Tucker\nJennifer Tilly\nDavid Strathairn\nEthan Embry",
      "id": "IVzuR4Gli-M",
      "channelName": "Popcornflix",
      "channelId": "UCVFYikepF-avelvuIaQ_lHA"
    }
  ],
  "relatedMovies": [],
  "collections": [],
  "is_curated": false,
  "verified": false,
  "lastUpdated": "2025-12-26T21:51:29.942Z"
}